{
  "sourceId": "19a6824d-5503-8074-95fd-dfd9e1c7725f",
  "targetId": "20a6824d-5503-8128-b09f-f8083e72cb20",
  "status": "success",
  "syncedAt": "2025-06-06T17:04:25.101Z",
  "sourceDbId": "1136824d550380f9a578cec5e8a871d0",
  "sourceDbName": "SM Tasks",
  "targetDbId": "1906824d5503817f868afa7f961a6f8f",
  "targetDbName": "CENT Tasks",
  "type": "tasks_SM",
  "sourcePageName": "send harper ideas",
  "sourcePageIcon": "",
  "targetPageName": "send harper ideas",
  "targetPageIcon": "",
  "notes": ""
}